LICENSE
MANIFEST.in
README.rst
setup.cfg
setup.py
Notable.egg-info/PKG-INFO
Notable.egg-info/SOURCES.txt
Notable.egg-info/dependency_links.txt
Notable.egg-info/top_level.txt
notable/.app.py.swp
notable/.bottle.py.swp
notable/__init__.py
notable/__init__.pyc
notable/app.py
notable/app.pyc
notable/bottle.py
notable/bottle.pyc
notable/crypt.py
notable/crypt.pyc
notable/db.py
notable/db.pyc
notable/editor.pyc
notable/__pycache__/__init__.cpython-32.pyc
notable/__pycache__/app.cpython-32.pyc
notable/__pycache__/bottle.cpython-32.pyc
notable/__pycache__/crypt.cpython-32.pyc
notable/__pycache__/db.cpython-32.pyc
notable/static/css/.style.css.swp
notable/static/css/style.css
notable/static/img/edit-paste.png
notable/static/img/encrypted.png
notable/static/js/main.js
notable/static/js/collections/notes.js
notable/static/js/models/note.js
notable/static/js/views/.noteTab.js.swp
notable/static/js/views/note.js
notable/static/js/views/password.js
notable/static/js/views/row.js
notable/static/js/views/search.js
notable/static/js/views/table.js
notable/static/lib/backbone.js
notable/static/lib/jquery.js
notable/static/lib/mousetrap.min.js
notable/static/lib/underscore.js
notable/static/lib/ace/src-min/ace.js
notable/static/lib/ace/src-min/ext-elastic_tabstops_lite.js
notable/static/lib/ace/src-min/ext-emmet.js
notable/static/lib/ace/src-min/ext-keybinding_menu.js
notable/static/lib/ace/src-min/ext-language_tools.js
notable/static/lib/ace/src-min/ext-modelist.js
notable/static/lib/ace/src-min/ext-options.js
notable/static/lib/ace/src-min/ext-searchbox.js
notable/static/lib/ace/src-min/ext-settings_menu.js
notable/static/lib/ace/src-min/ext-spellcheck.js
notable/static/lib/ace/src-min/ext-split.js
notable/static/lib/ace/src-min/ext-static_highlight.js
notable/static/lib/ace/src-min/ext-statusbar.js
notable/static/lib/ace/src-min/ext-textarea.js
notable/static/lib/ace/src-min/ext-themelist.js
notable/static/lib/ace/src-min/ext-whitespace.js
notable/static/lib/ace/src-min/keybinding-emacs.js
notable/static/lib/ace/src-min/keybinding-vim.js
notable/static/lib/ace/src-min/mode-abap.js
