Metadata-Version: 1.1
Name: Notable
Version: 0.4.2
Summary: A very simple note taking application
Home-page: https://github.com/jmcfarlane/Notable
Author: John McFarlane
Author-email: john.mcfarlane@rockfloat.com
License: UNKNOWN
Download-URL: http://pypi.python.org/packages/source/N/Notable/Notable-0.4.2.tar.gz
Platform: UNKNOWN
Classifier: Development Status :: 2 - Pre-Alpha
Classifier: Intended Audience :: Developers
Classifier: License :: OSI Approved :: MIT License
Classifier: Operating System :: OS Independent
Classifier: Programming Language :: Python
Classifier: Topic :: Internet :: WWW/HTTP
Classifier: Intended Audience :: End Users/Desktop
Classifier: Topic :: Office/Business :: News/Diary
Classifier: Topic :: Security :: Cryptography
Classifier: Topic :: Utilities
